rpgmaincore/.gitattributes
rpgmaincore/.gitignore
rpgmaincore/__init__.py
rpgmaincore/characters.py
rpgmaincore/competences.py
rpgmaincore/races.py
rpgmaincore-0.0.6.dist-info/METADATA
rpgmaincore-0.0.6.dist-info/WHEEL
rpgmaincore-0.0.6.dist-info/licenses/LICENSE
rpgmaincore-0.0.6.dist-info/RECORD
