Metadata-Version: 2.1
Name: rpgmaincore
Version: 0.0.6
Summary: a library to create rpg
Project-URL: Homepage, https://github.com/riioze/rpgmaincore
Project-URL: Bug Tracker, https://github.com/riioze/rpgmaincore/issues
Author-email: lopotichaaaa <riioze0@gmail.com>
License: Copyright (c) 2018 The Python Packaging Authority
Classifier: License :: OSI Approved :: MIT License
Classifier: Operating System :: OS Independent
Classifier: Programming Language :: Python :: 3
Requires-Python: >=3.7
